datapreprocessing/__init__.py
datapreprocessing/data_generate.py
datapreprocessing/data_load.py
datapreprocessing/test.py
visualplots/__init__.py
visualplots/plots.py
hlkdatapreprocessing-0.3.dist-info/METADATA
hlkdatapreprocessing-0.3.dist-info/WHEEL
hlkdatapreprocessing-0.3.dist-info/top_level.txt
hlkdatapreprocessing-0.3.dist-info/RECORD
