Metadata-Version: 2.1
Name: hlkdatapreprocessing
Version: 0.3
Summary: 用于进行数据生成、数据初步处理
Author: code dancer
